GEMEditor/GEMEditor.cfg
GEMEditor/__init__.py
GEMEditor/conftest.py
GEMEditor/icons_rc.py
GEMEditor/run.py
GEMEditor/analysis/__init__.py
GEMEditor/analysis/formula.py
GEMEditor/analysis/model_test.py
GEMEditor/analysis/duplicates/__init__.py
GEMEditor/analysis/duplicates/dialog.py
GEMEditor/analysis/duplicates/functions.py
GEMEditor/analysis/duplicates/ui/TreeViewDialog.py
GEMEditor/analysis/duplicates/ui/__init__.py
GEMEditor/analysis/statistics/__init__.py
GEMEditor/analysis/statistics/dialog.py
GEMEditor/analysis/statistics/functions.py
GEMEditor/analysis/statistics/test/__init__.py
GEMEditor/analysis/statistics/test/test_functions.py
GEMEditor/analysis/statistics/ui/StatisticsDialog.py
GEMEditor/analysis/statistics/ui/__init__.py
GEMEditor/base/__init__.py
GEMEditor/base/classes.py
GEMEditor/base/delegates.py
GEMEditor/base/dialogs.py
GEMEditor/base/functions.py
GEMEditor/base/proxy.py
GEMEditor/base/tables.py
GEMEditor/base/validators.py
GEMEditor/base/views.py
GEMEditor/base/widgets.py
GEMEditor/base/test/__init__.py
GEMEditor/base/test/fixtures.py
GEMEditor/base/test/test_classes.py
GEMEditor/base/test/test_dialogs.py
GEMEditor/base/test/test_functions.py
GEMEditor/base/test/test_validators.py
GEMEditor/base/ui/DataFrameDialog.py
GEMEditor/base/ui/EmptyDialogHorzButtons.py
GEMEditor/base/ui/ListDisplayDialog.py
GEMEditor/base/ui/TableDisplayWidgetAddDel.py
GEMEditor/base/ui/TableSearchWidget.py
GEMEditor/base/ui/__init__.py
GEMEditor/connect/__init__.py
GEMEditor/connect/kegg.py
GEMEditor/connect/ncbi.py
GEMEditor/connect/pmc.py
GEMEditor/connect/pubmed.py
GEMEditor/connect/urldownloader.py
GEMEditor/database/__init__.py
GEMEditor/database/base.py
GEMEditor/database/create.py
GEMEditor/database/load.py
GEMEditor/database/model.py
GEMEditor/database/query.py
GEMEditor/database/tables.py
GEMEditor/database/match/__init__.py
GEMEditor/database/match/dialog.py
GEMEditor-0.4.0.dist-info/DESCRIPTION.rst
GEMEditor-0.4.0.dist-info/METADATA
GEMEditor-0.4.0.dist-info/RECORD
GEMEditor-0.4.0.dist-info/WHEEL
GEMEditor-0.4.0.dist-info/metadata.json
GEMEditor-0.4.0.dist-info/top_level.txt
