Metadata-Version: 2.0
Name: GEMEditor
Version: 0.4.0
Summary: A graphical editor for the reconstruction, annotation and testing of genome-scale models
Home-page: https://github.com/JuBra/GEMEditor
Author: Julian Brandl
Author-email: jubra@bio.dtu.dk
License: GPL
Keywords: metabolism biology
Platform: GNU/Linux
Platform: Mac OS X >= 10.7
Platform: Microsoft Windows >= 7
Classifier: Development Status :: 3 - Alpha
Classifier: Intended Audience :: Science/Research
Classifier: Programming Language :: Python :: 3.5
Classifier: Operating System :: Microsoft :: Windows
Classifier: Operating System :: MacOS
Classifier: Operating System :: Unix
Classifier: License :: OSI Approved :: GNU General Public License v3 (GPLv3)
Classifier: Topic :: Scientific/Engineering
Classifier: Topic :: Scientific/Engineering :: Bio-Informatics
Requires-Dist: PyQt5
Requires-Dist: cobra
Requires-Dist: escher
Requires-Dist: lxml
Requires-Dist: networkx
Requires-Dist: numpy
Requires-Dist: sqlalchemy
